<Properties StartupConfiguration="{4C8F8B92-E343-A0B9-C0DF-F2B365568AB0}|">
  <MonoDevelop.Ide.Workbench ActiveDocument="Assets/musicController.cs">
    <Files>
      <File FileName="Assets/musicController.cs" Line="61" Column="37" />
    </Files>
    <Pads>
      <Pad Id="ProjectPad">
        <State name="__root__">
          <Node name="music-player-dmd" expanded="True">
            <Node name="Assets" expanded="True">
              <Node name="musicController.cs" selected="True" />
            </Node>
          </Node>
        </State>
      </Pad>
    </Pads>
  </MonoDevelop.Ide.Workbench>
  <MonoDevelop.Ide.DebuggingService.PinnedWatches />
  <MonoDevelop.Ide.Workspace ActiveConfiguration="Debug" />
  <MonoDevelop.Ide.ItemProperties.Assembly-CSharp PreferredExecutionTarget="c8e3ab76-4b9d-4fb8-8405-0230088977b5" />
  <MonoDevelop.Ide.DebuggingService.Breakpoints>
    <BreakpointStore />
  </MonoDevelop.Ide.DebuggingService.Breakpoints>
  <MultiItemStartupConfigurations />
</Properties>